svelte2jupyter/.gitignore
svelte2jupyter/__init__.py
svelte2jupyter/buildComponents.js
svelte2jupyter/component_utils.py
svelte2jupyter/constants.py
svelte2jupyter/npm_utils.py
svelte2jupyter/package.json
svelte2jupyter/package.py
svelte2jupyter/packaged_component.py
svelte2jupyter/randomize_hash_id.py
svelte2jupyter/render_component.py
svelte2jupyter/svelte_jupyter_widget.py
svelte2jupyter/vite.config.js
svelte2jupyter-0.1.1.dist-info/LICENSE
svelte2jupyter-0.1.1.dist-info/METADATA
svelte2jupyter-0.1.1.dist-info/WHEEL
svelte2jupyter-0.1.1.dist-info/RECORD
