Metadata-Version: 2.1
Name: svelte2jupyter
Version: 0.1.1
Summary: Render svelte components inside of Jupyter notebooks.
Author: Jared Wilber
Author-email: jdwlbr@gmail.com
Requires-Python: >=3.8,<4.0
Classifier: Programming Language :: Python :: 3
Classifier: Programming Language :: Python :: 3.8
Classifier: Programming Language :: Python :: 3.9
Classifier: Programming Language :: Python :: 3.10
Classifier: Programming Language :: Python :: 3.11
